fhir_pyrate/__init__.py
fhir_pyrate/ahoy.py
fhir_pyrate/dicom_downloader.py
fhir_pyrate/miner.py
fhir_pyrate/pirate.py
fhir_pyrate/util/__init__.py
fhir_pyrate/util/bundle_processing_templates.py
fhir_pyrate/util/fhirobj.py
fhir_pyrate/util/imports.py
fhir_pyrate/util/token_auth.py
fhir_pyrate/util/util.py
fhir_pyrate-0.2.3.dist-info/LICENSE
fhir_pyrate-0.2.3.dist-info/METADATA
fhir_pyrate-0.2.3.dist-info/WHEEL
fhir_pyrate-0.2.3.dist-info/RECORD
