Metadata-Version: 2.1
Name: fhir-pyrate
Version: 0.2.3
Summary: FHIR-PYrate is a package that provides a high-level API to query FHIR Servers for bundles of resources and return the structured information as pandas DataFrames. It can also be used to filter resources using RegEx and SpaCy and download DICOM studies and series.
Home-page: https://github.com/UMEssen/FHIR-PYrate
License: MIT
Keywords: python,fhir,data-science,fhirpath,healthcare
Author: Rene Hosch
Author-email: rene.hosch@uk-essen.de
Requires-Python: >=3.10,<4.0
Classifier: License :: OSI Approved :: MIT License
Classifier: Programming Language :: Python :: 3
Classifier: Programming Language :: Python :: 3.10
Classifier: Programming Language :: Python :: 3.11
Classifier: Programming Language :: Python :: 3.12
Classifier: Programming Language :: Python :: 3.13
Provides-Extra: all
Provides-Extra: downloader
Provides-Extra: miner
Requires-Dist: PyJWT (>=2.4.0,<3.0.0)
Requires-Dist: SimpleITK (>=2.0.2,<3.0.0) ; extra == "downloader" or extra == "all"
Requires-Dist: dicomweb-client (>=0.52.0,<0.53.0) ; extra == "downloader" or extra == "all"
Requires-Dist: fhirpathpy (>=0.2.2,<0.3.0)
Requires-Dist: numpy (>=2.0.0,<3.0.0)
Requires-Dist: pandas (>=2.0.0,<3.0.0)
Requires-Dist: pydicom (>=2.1.2,<3.0.0) ; extra == "downloader" or extra == "all"
Requires-Dist: requests (>=2.31.0,<3.0.0)
Requires-Dist: requests-cache (>=0.9.7,<0.10.0)
Requires-Dist: spacy (>=3.0.6,<4.0.0) ; extra == "miner" or extra == "all"
Requires-Dist: tqdm (>=4.56.0,<5.0.0)
Project-URL: Repository, https://github.com/UMEssen/FHIR-PYrate
